setup.cfg
setup.py
boto3_policygen/__init__.py
boto3_policygen/iam.py
boto3_policygen.egg-info/PKG-INFO
boto3_policygen.egg-info/SOURCES.txt
boto3_policygen.egg-info/dependency_links.txt
boto3_policygen.egg-info/requires.txt
boto3_policygen.egg-info/top_level.txt
test/test_policy_gen.py